Klingonprints/Theme.py
Klingonprints/Translate.py
Klingonprints/__init__.py
Klingonprints-0.1.1.dist-info/METADATA
Klingonprints-0.1.1.dist-info/WHEEL
Klingonprints-0.1.1.dist-info/top_level.txt
Klingonprints-0.1.1.dist-info/RECORD
